<shortcuts>
	<shortcut>
		<defaultID>7</defaultID>
		<label>7</label>
		<label2>פריט תפריט נפוץ</label2>
		<icon>DefaultFolder.png</icon>
		<thumb />
		<action>ActivateWindow(FileManager)</action>
		</shortcut>
	<shortcut>
		<defaultID>13200</defaultID>
		<label>עידכון מערכת</label>
		<label2>פריטים מותאמים אישית</label2>
		<icon>special://home/media/update.jpg</icon>
		<thumb />
		<action>RunAddOn(script.system_updater)</action>
		</shortcut>
	<shortcut>
		<defaultID>10007</defaultID>
		<label>10007</label>
		<label2>פריט תפריט נפוץ</label2>
		<icon>special://skin/extras/icons/sysinfo.png</icon>
		<thumb />
		<action>ActivateWindow(SystemInfo)</action>
		</shortcut>
	<shortcut>
		<defaultID>14111</defaultID>
		<label>14111</label>
		<label2>פריט תפריט נפוץ</label2>
		<icon>DefaultShortcut.png</icon>
		<thumb />
		<action>ActivateWindow(EventLog,events://,return)</action>
		</shortcut>
	<shortcut>
		<defaultID />
		<label>סייר הרחבות</label>
		<label2>פריטים מותאמים אישית</label2>
		<icon>DefaultShortcut.png</icon>
		<thumb />
		<action>ActivateWindow(AddonBrowser)</action>
		</shortcut>
	<shortcut>
		<defaultID />
		<label>ניקוי קאש</label>
		<label2>פריטים מותאמים אישית</label2>
		<icon>DefaultShortcut.png</icon>
		<thumb />
		<action>PlayMedia("plugin://plugin.video.cobra/?mode=clear_all_cache&amp;isFolder=false&amp;iconImage=https%3A%2F%2Fi.imgur.com%2FRDNxy36.png")</action>
		</shortcut>
	<shortcut>
		<defaultID />
		<label>הגדרות מעטפת</label>
		<label2>פריטים מותאמים אישית</label2>
		<icon>DefaultShortcut.png</icon>
		<thumb />
		<action>ActivateWindow(SkinSettings)</action>
		</shortcut>
	</shortcuts>
